[
  {
    "id": "pronunciation_mangwanani",
    "word": "mangwanani",
    "phonetic": "m-a-ng-w-a-n-a-n-i",
    "syllables": "ma-ngwa-na-ni",
    "tonePattern": "HL",
    "audioFile": "mangwanani.wav",
    "complexity": 9,
    "specialSounds": "[{\"token\":\"ng\",\"type\":\"prenasalized\",\"ipa\":\"ŋɡ\"}]",
    "pronunciationTips": [],
    "learningLevel": "Intermediate",
    "category": "Greetings",
    "translation": "good morning"
  },
  {
    "id": "pronunciation_masikati",
    "word": "masikati",
    "phonetic": "m-a-s-i-k-a-t-i",
    "syllables": "ma-si-ka-ti",
    "tonePattern": "HL",
    "audioFile": "masikati.wav",
    "complexity": 8,
    "specialSounds": "[]",
    "pronunciationTips": [],
    "learningLevel": "Intermediate",
    "category": "Greetings",
    "translation": "good afternoon"
  },
  {
    "id": "pronunciation_manheru",
    "word": "manheru",
    "phonetic": "m-a-n-h-e-r-u",
    "syllables": "ma-nhe-ru",
    "tonePattern": "HL",
    "audioFile": "manheru.wav",
    "complexity": 7,
    "specialSounds": "[]",
    "pronunciationTips": [],
    "learningLevel": "Intermediate",
    "category": "Greetings",
    "translation": "good evening"
  },
  {
    "id": "pronunciation_bhazi",
    "word": "bhazi",
    "phonetic": "bh-a-z-i",
    "syllables": "bha-zi",
    "tonePattern": "HL",
    "audioFile": "bhazi.wav",
    "complexity": 4,
    "specialSounds": "[{\"token\":\"bh\",\"type\":\"breathy\",\"ipa\":\"bʱ\"}]",
    "pronunciationTips": [],
    "learningLevel": "Beginner",
    "category": "Transport",
    "translation": "bus"
  },
  {
    "id": "pronunciation_svika",
    "word": "svika",
    "phonetic": "sv-i-k-a",
    "syllables": "svi-ka",
    "tonePattern": "HL",
    "audioFile": "svika.wav",
    "complexity": 4,
    "specialSounds": "[{\"token\":\"sv\",\"type\":\"whistled\",\"ipa\":\"swhistling\"}]",
    "pronunciationTips": [],
    "learningLevel": "Beginner",
    "category": "Movement",
    "translation": "arrive"
  },
  {
    "id": "pronunciation_zvino",
    "word": "zvino",
    "phonetic": "zv-i-n-o",
    "syllables": "zvi-no",
    "tonePattern": "HL",
    "audioFile": "zvino.wav",
    "complexity": 4,
    "specialSounds": "[{\"token\":\"zv\",\"type\":\"whistled\",\"ipa\":\"zwhistling\"}]",
    "pronunciationTips": [],
    "learningLevel": "Beginner",
    "category": "Time",
    "translation": "now"
  },
  {
    "id": "pronunciation_tsvaira",
    "word": "tsvaira",
    "phonetic": "tsv-a-i-r-a",
    "syllables": "tsva-i-ra",
    "tonePattern": "HL",
    "audioFile": "tsvaira.wav",
    "complexity": 5,
    "specialSounds": "[]",
    "pronunciationTips": [],
    "learningLevel": "Beginner",
    "category": "Action",
    "translation": "drive"
  },
  {
    "id": "pronunciation_kuudza",
    "word": "kuudza",
    "phonetic": "k-u-u-dz-a",
    "syllables": "ku-u-dza",
    "tonePattern": "HL",
    "audioFile": "kuudza.wav",
    "complexity": 5,
    "specialSounds": "[]",
    "pronunciationTips": [],
    "learningLevel": "Beginner",
    "category": "Communication",
    "translation": "to tell"
  },
  {
    "id": "pronunciation_mbira",
    "word": "mbira",
    "phonetic": "mb-i-r-a",
    "syllables": "mbi-ra",
    "tonePattern": "HL",
    "audioFile": "mbira.wav",
    "complexity": 4,
    "specialSounds": "[{\"token\":\"mb\",\"type\":\"prenasalized\",\"ipa\":\"mb\"}]",
    "pronunciationTips": [],
    "learningLevel": "Beginner",
    "category": "Music",
    "translation": "thumb piano"
  },
  {
    "id": "pronunciation_ndimi",
    "word": "ndimi",
    "phonetic": "nd-i-m-i",
    "syllables": "ndi-mi",
    "tonePattern": "HL",
    "audioFile": "ndimi.wav",
    "complexity": 4,
    "specialSounds": "[{\"token\":\"nd\",\"type\":\"prenasalized\",\"ipa\":\"nd\"}]",
    "pronunciationTips": [],
    "learningLevel": "Beginner",
    "category": "Pronouns",
    "translation": "you (plural)"
  },
  {
    "id": "pronunciation_ngoma",
    "word": "ngoma",
    "phonetic": "ng-o-m-a",
    "syllables": "ngo-ma",
    "tonePattern": "HL",
    "audioFile": "ngoma.wav",
    "complexity": 4,
    "specialSounds": "[{\"token\":\"ng\",\"type\":\"prenasalized\",\"ipa\":\"ŋɡ\"}]",
    "pronunciationTips": [],
    "learningLevel": "Beginner",
    "category": "Music",
    "translation": "drum"
  },
  {
    "id": "pronunciation_ndatenda",
    "word": "ndatenda",
    "phonetic": "nd-a-t-e-nd-a",
    "syllables": "nda-te-nda",
    "tonePattern": "HL",
    "audioFile": "ndatenda.wav",
    "complexity": 6,
    "specialSounds": "[{\"token\":\"nd\",\"type\":\"prenasalized\",\"ipa\":\"nd\"},{\"token\":\"nd\",\"type\":\"prenasalized\",\"ipa\":\"nd\"}]",
    "pronunciationTips": [],
    "learningLevel": "Beginner",
    "category": "Courtesy",
    "translation": "thank you"
  },
  {
    "id": "pronunciation_zvakanaka",
    "word": "zvakanaka",
    "phonetic": "zv-a-k-a-n-a-k-a",
    "syllables": "zva-ka-na-ka",
    "tonePattern": "HL",
    "audioFile": "zvakanaka.wav",
    "complexity": 8,
    "specialSounds": "[{\"token\":\"zv\",\"type\":\"whistled\",\"ipa\":\"zwhistling\"}]",
    "pronunciationTips": [],
    "learningLevel": "Intermediate",
    "category": "Responses",
    "translation": "fine/good"
  },
  {
    "id": "pronunciation_pamusoroi",
    "word": "pamusoroi",
    "phonetic": "p-a-m-u-s-o-r-o-i",
    "syllables": "pa-mu-so-ro-i",
    "tonePattern": "HL",
    "audioFile": "pamusoroi.wav",
    "complexity": 9,
    "specialSounds": "[]",
    "pronunciationTips": [],
    "learningLevel": "Intermediate",
    "category": "Courtesy",
    "translation": "excuse me"
  },
  {
    "id": "pronunciation_sara",
    "word": "sara",
    "phonetic": "s-a-r-a",
    "syllables": "sa-ra",
    "tonePattern": "HL",
    "audioFile": "sara.wav",
    "complexity": 4,
    "specialSounds": "[]",
    "pronunciationTips": [],
    "learningLevel": "Beginner",
    "category": "Action",
    "translation": "remain"
  }
]